CHANGES.rst
CONTRIBUTORS.rst
MANIFEST.in
README.rst
setup.cfg
setup.py
docs/LICENSE.GPL
docs/LICENSE.txt
src/interlegis/__init__.py
src/interlegis.intranetmodelo.departments.egg-info/PKG-INFO
src/interlegis.intranetmodelo.departments.egg-info/SOURCES.txt
src/interlegis.intranetmodelo.departments.egg-info/dependency_links.txt
src/interlegis.intranetmodelo.departments.egg-info/entry_points.txt
src/interlegis.intranetmodelo.departments.egg-info/namespace_packages.txt
src/interlegis.intranetmodelo.departments.egg-info/not-zip-safe
src/interlegis.intranetmodelo.departments.egg-info/requires.txt
src/interlegis.intranetmodelo.departments.egg-info/top_level.txt
src/interlegis/intranetmodelo/__init__.py
src/interlegis/intranetmodelo/departments/__init__.py
src/interlegis/intranetmodelo/departments/config.py
src/interlegis/intranetmodelo/departments/configure.zcml
src/interlegis/intranetmodelo/departments/dependencies.zcml
src/interlegis/intranetmodelo/departments/interfaces.py
src/interlegis/intranetmodelo/departments/profiles.zcml
src/interlegis/intranetmodelo/departments/testing.py
src/interlegis/intranetmodelo/departments/browser/__init__.py
src/interlegis/intranetmodelo/departments/browser/view.py
src/interlegis/intranetmodelo/departments/browser/templates/view.pt
src/interlegis/intranetmodelo/departments/content/__init__.py
src/interlegis/intranetmodelo/departments/content/department.py
src/interlegis/intranetmodelo/departments/content/schema/Department.xml
src/interlegis/intranetmodelo/departments/content/schema/__init__.py
src/interlegis/intranetmodelo/departments/locales/interlegis.intranetmodelo.departments.pot
src/interlegis/intranetmodelo/departments/locales/manual.pot
src/interlegis/intranetmodelo/departments/locales/plone.pot
src/interlegis/intranetmodelo/departments/locales/pt_BR/LC_MESSAGES/interlegis.intranetmodelo.departments.po
src/interlegis/intranetmodelo/departments/locales/pt_BR/LC_MESSAGES/plone.po
src/interlegis/intranetmodelo/departments/profiles/default/browserlayer.xml
src/interlegis/intranetmodelo/departments/profiles/default/contentrules.xml
src/interlegis/intranetmodelo/departments/profiles/default/metadata.xml
src/interlegis/intranetmodelo/departments/profiles/default/rolemap.xml
src/interlegis/intranetmodelo/departments/profiles/default/types.xml
src/interlegis/intranetmodelo/departments/profiles/default/types/Department.xml
src/interlegis/intranetmodelo/departments/profiles/uninstall/interlegis.intranetmodelo.departments.txt
